README.md
setup.py
src/presenzialo/__init__.py
src/presenzialo/presenzialo.py
src/presenzialo/presenzialo_address.py
src/presenzialo/presenzialo_args.py
src/presenzialo/presenzialo_auth.py
src/presenzialo/presenzialo_bot.py
src/presenzialo/presenzialo_config.py
src/presenzialo/presenzialo_day.py
src/presenzialo/presenzialo_id.py
src/presenzialo/presenzialo_utils.py
src/presenzialo/presenzialo_web.py
src/presenzialo/test.py
src/presenzialo.egg-info/PKG-INFO
src/presenzialo.egg-info/SOURCES.txt
src/presenzialo.egg-info/dependency_links.txt
src/presenzialo.egg-info/entry_points.txt
src/presenzialo.egg-info/requires.txt
src/presenzialo.egg-info/top_level.txt
src/presenzialo/logs/__init__.py
src/presenzialo/logs/config.py
src/presenzialo/logs/daylog.py
src/presenzialo/logs/dayloglist.py
src/presenzialo/logs/logs.py
src/presenzialo/logs/test.py
src/presenzialo/logs/test_main.py
src/presenzialo/logs/dayutils/__init__.py
src/presenzialo/logs/dayutils/dayutils.py