Metadata-Version: 1.2
Name: presenzialo
Version: 0.4.1
Summary: presence web manager
Home-page: https://github.com/so07/presenzialo
Author: so07
Author-email: 
Maintainer: so07
License: UNKNOWN
Platform: UNKNOWN
Classifier: Development Status :: 3 - Alpha
Classifier: Programming Language :: Python :: 3
Requires: requests
